[
  {
    "id": 32,
    "name": "CROP MESH TANK",
    "category": "Top",
    "sex": "women",
    "new": false,
    "off": true,
    "accessory": false,
    "colorId": 3,
    "colorName": "White",
    "images": [
      "/src/assets/images/women/post/tops/crop-mesh-tank-1.jpg"
    ],
    "price": 21
  },
  {
    "id": 34,
    "name": "MOTIVATION TEE",
    "category": "Top",
    "sex": "women",
    "new": true,
    "off": true,
    "accessory": false,
    "colorId": 2,
    "colorName": "Black",
    "images": [
      "/src/assets/images/women/post/tops/motivation-tee-1.jpg"
    ],
    "price": 21
  },
  {
    "id": 35,
    "name": "STRAPPY CROP",
    "category": "Top",
    "sex": "women",
    "new": false,
    "off": true,
    "accessory": false,
    "colorId": 1,
    "colorName": "Pink",
    "images": [
      "/src/assets/images/women/post/tops/strappy-crop-cami-tank-1.jpg"
    ],
    "price": 21
  },
  {
    "id": 36,
    "name": "SWOOSH LIGHT",
    "category": "Top",
    "sex": "women",
    "new": true,
    "off": true,
    "accessory": false,
    "colorId": 3,
    "colorName": "Violet",
    "images": [
      "/src/assets/images/women/post/tops/swoosh-light-1.jpg"
    ],
    "price": 21
  },
  {
    "id": 37,
    "name": "TINY TWIST BRA",
    "category": "Top",
    "sex": "women",
    "new": false,
    "off": true,
    "accessory": false,
    "colorId": 3,
    "colorName": "Green",
    "images": [
      "/src/assets/images/women/post/tops/tiny-twist-bra-1.jpg"
    ],
    "price": 21
  },
  {
    "id": 38,
    "name": "VITAL SEAMLESS",
    "category": "Top",
    "sex": "women",
    "new": false,
    "off": true,
    "accessory": false,
    "colorId": 3,
    "colorName": "Green",
    "images": [
      "/src/assets/images/women/post/tops/vital-seamless-1.jpg"
    ],
    "price": 21
  }
]